py_imessage/__init__.py
py_imessage/db_conn.py
py_imessage/imessage.py
py_imessage/osascript/check_imessage.js
py_imessage/osascript/send_message.js
py_iMessage-1.7.dist-info/LICENSE.txt
py_iMessage-1.7.dist-info/METADATA
py_iMessage-1.7.dist-info/WHEEL
py_iMessage-1.7.dist-info/top_level.txt
py_iMessage-1.7.dist-info/RECORD
